{
  "annonce": {
    "gestion": {
      "nojo": "08-237727",
      "rappel": null,
      "r2": "4",
      "r3": "91",
      "tetierr3": "91 - Essonne",
      "r4": "9",
      "tetierr4": "Avis d'attribution",
      "k1": null,
      "doublon": null,
      "k9": null,
      "numann": "97",
      "nomhtml": "/2008/MPC/MPC20080082/200810130097C.HTM"
    },
    "donnees": {
      "titreandINFOAndTYPEACTIVITEORG": [
        {
          "name": "INFO",
          "declaredType": "fr.gouv.dila.opendata.api.model.Boamp.Boamp_v110.Info",
          "scope": "fr.gouv.dila.opendata.api.model.Boamp.Boamp_v110.Annonce$DONNEES",
          "value": {
            "travauxandFOURNITURESAndSERVICES": [
              {
                "name": "ETAT",
                "declaredType": "java.lang.String",
                "scope": "fr.gouv.dila.opendata.api.model.Boamp.Boamp_v110.Info",
                "value": "",
                "nil": false,
                "globalScope": false,
                "typeSubstituted": false
              }
            ]
          },
          "nil": false,
          "globalScope": false,
          "typeSubstituted": false
        },
        {
          "name": "IDENT",
          "declaredType": "fr.gouv.dila.opendata.api.model.Boamp.Boamp_v110.Identite",
          "scope": "fr.gouv.dila.opendata.api.model.Boamp.Boamp_v110.Annonce$DONNEES",
          "value": {
            "titreandNOMAndCODEIDENTNATIONAL": [
              {
                "name": "TITRE",
                "declaredType": "java.lang.String",
                "scope": "fr.gouv.dila.opendata.api.model.Boamp.Boamp_v110.Identite",
                "value": "Nom et adresse officiels de l'organisme acheteur : ",
                "nil": false,
                "globalScope": false,
                "typeSubstituted": false
              },
              {
                "name": "NOM",
                "declaredType": "java.lang.String",
                "scope": "fr.gouv.dila.opendata.api.model.Boamp.Boamp_v110.Identite",
                "value": "MINDEF/simmad.",
                "nil": false,
                "globalScope": false,
                "typeSubstituted": false
              },
              {
                "name": "PRM",
                "declaredType": "java.lang.String",
                "scope": "fr.gouv.dila.opendata.api.model.Boamp.Boamp_v110.Identite",
                "value": "M. le chef du service des contrats et des finances de la SIMMAD,",
                "nil": false,
                "globalScope": false,
                "typeSubstituted": false
              },
              {
                "name": "ADRESSE",
                "declaredType": "java.lang.String",
                "scope": "fr.gouv.dila.opendata.api.model.Boamp.Boamp_v110.Identite",
                "value": "service des contrats et des finances de la SIMMAD base a\u00e9rienne 217, ",
                "nil": false,
                "globalScope": false,
                "typeSubstituted": false
              },
              {
                "name": "CP",
                "declaredType": "java.lang.String",
                "scope": "fr.gouv.dila.opendata.api.model.Boamp.Boamp_v110.Identite",
                "value": "91224",
                "nil": false,
                "globalScope": false,
                "typeSubstituted": false
              },
              {
                "name": "VILLE",
                "declaredType": "java.lang.String",
                "scope": "fr.gouv.dila.opendata.api.model.Boamp.Boamp_v110.Identite",
                "value": "Br\u00e9tigny-sur-Orge Cedex, ",
                "nil": false,
                "globalScope": false,
                "typeSubstituted": false
              },
              {
                "name": "TEL",
                "declaredType": "java.lang.String",
                "scope": "fr.gouv.dila.opendata.api.model.Boamp.Boamp_v110.Identite",
                "value": "01-69-23-88-93, ",
                "nil": false,
                "globalScope": false,
                "typeSubstituted": false
              },
              {
                "name": "FAX",
                "declaredType": "java.lang.String",
                "scope": "fr.gouv.dila.opendata.api.model.Boamp.Boamp_v110.Identite",
                "value": "01-69-23-86-60, ",
                "nil": false,
                "globalScope": false,
                "typeSubstituted": false
              },
              {
                "name": "MEL",
                "declaredType": "java.lang.String",
                "scope": "fr.gouv.dila.opendata.api.model.Boamp.Boamp_v110.Identite",
                "value": "scf.simmad@wanadoo.fr.",
                "nil": false,
                "globalScope": false,
                "typeSubstituted": false
              }
            ]
          },
          "nil": false,
          "globalScope": false,
          "typeSubstituted": false
        },
        {
          "name": "TYPE_ACTIVITE_ORG",
          "declaredType": "fr.gouv.dila.opendata.api.model.Boamp.Boamp_v110.EnumActiviteOrganisationnelle",
          "scope": "fr.gouv.dila.opendata.api.model.Boamp.Boamp_v110.Annonce$DONNEES",
          "value": {
            "pouvoiradjudicateurandENTITEADJUDICATRICEAndACTSERVADMPUB": [
              {
                "name": "POUVOIR_ADJUDICATEUR",
                "declaredType": "java.lang.String",
                "scope": "fr.gouv.dila.opendata.api.model.Boamp.Boamp_v110.EnumActiviteOrganisationnelle",
                "value": "",
                "nil": false,
                "globalScope": false,
                "typeSubstituted": false
              },
              {
                "name": "DEF",
                "declaredType": "java.lang.String",
                "scope": "fr.gouv.dila.opendata.api.model.Boamp.Boamp_v110.EnumActiviteOrganisationnelle",
                "value": "",
                "nil": false,
                "globalScope": false,
                "typeSubstituted": false
              }
            ]
          },
          "nil": false,
          "globalScope": false,
          "typeSubstituted": false
        },
        {
          "name": "RECTIF",
          "declaredType": "fr.gouv.dila.opendata.api.model.Boamp.Boamp_v110.Rectificatif",
          "scope": "fr.gouv.dila.opendata.api.model.Boamp.Boamp_v110.Annonce$DONNEES",
          "value": {
            "parutandPARUTIONAndTYPE": [
              {
                "name": "NO_ANN",
                "declaredType": "java.lang.String",
                "scope": "fr.gouv.dila.opendata.api.model.Boamp.Boamp_v110.Rectificatif",
                "value": "95",
                "nil": false,
                "globalScope": false,
                "typeSubstituted": false
              },
              {
                "name": "PARUT",
                "declaredType": "java.lang.String",
                "scope": "fr.gouv.dila.opendata.api.model.Boamp.Boamp_v110.Rectificatif",
                "value": "123",
                "nil": false,
                "globalScope": false,
                "typeSubstituted": false
              },
              {
                "name": "TYPE",
                "declaredType": "java.lang.String",
                "scope": "fr.gouv.dila.opendata.api.model.Boamp.Boamp_v110.Rectificatif",
                "value": "B",
                "nil": false,
                "globalScope": false,
                "typeSubstituted": false
              },
              {
                "name": "DATE",
                "declaredType": "java.lang.String",
                "scope": "fr.gouv.dila.opendata.api.model.Boamp.Boamp_v110.Rectificatif",
                "value": "26 juin 2008",
                "nil": false,
                "globalScope": false,
                "typeSubstituted": false
              },
              {
                "name": "AUTRES",
                "declaredType": "java.lang.String",
                "scope": "fr.gouv.dila.opendata.api.model.Boamp.Boamp_v110.Rectificatif",
                "value": ".",
                "nil": false,
                "globalScope": false,
                "typeSubstituted": false
              }
            ]
          },
          "nil": false,
          "globalScope": false,
          "typeSubstituted": false
        },
        {
          "name": "INFO",
          "declaredType": "fr.gouv.dila.opendata.api.model.Boamp.Boamp_v110.Info",
          "scope": "fr.gouv.dila.opendata.api.model.Boamp.Boamp_v110.Annonce$DONNEES",
          "value": {
            "travauxandFOURNITURESAndSERVICES": [
              {
                "name": "REFERENCE",
                "declaredType": "java.lang.String",
                "scope": "fr.gouv.dila.opendata.api.model.Boamp.Boamp_v110.Info",
                "value": "08 92 837.",
                "nil": false,
                "globalScope": false,
                "typeSubstituted": false
              }
            ]
          },
          "nil": false,
          "globalScope": false,
          "typeSubstituted": false
        },
        {
          "name": "OBJET",
          "declaredType": "fr.gouv.dila.opendata.api.model.Boamp.Boamp_v110.Objet",
          "scope": "fr.gouv.dila.opendata.api.model.Boamp.Boamp_v110.Annonce$DONNEES",
          "value": {
            "titreandOBJETCOMPLETAndTITREMARCHE": [
              {
                "name": "TITRE",
                "declaredType": "java.lang.String",
                "scope": "fr.gouv.dila.opendata.api.model.Boamp.Boamp_v110.Objet",
                "value": "Objet du march\u00e9 :",
                "nil": false,
                "globalScope": false,
                "typeSubstituted": false
              },
              {
                "name": "OBJET_COMPLET",
                "declaredType": "java.lang.String",
                "scope": "fr.gouv.dila.opendata.api.model.Boamp.Boamp_v110.Objet",
                "value": "mise \u00e0 disposition et maintenance de deux v\u00e9hicules d\u00e9givrage et antigivrage pour a\u00e9ronef sur la base a\u00e9rienne de Villacoublay pour une p\u00e9riode comprise entre le 6 octobre 2008 et le 6 mars 2009.",
                "nil": false,
                "globalScope": false,
                "typeSubstituted": false
              },
              {
                "name": "LOC",
                "declaredType": "java.lang.String",
                "scope": "fr.gouv.dila.opendata.api.model.Boamp.Boamp_v110.Objet",
                "value": "",
                "nil": false,
                "globalScope": false,
                "typeSubstituted": false
              }
            ]
          },
          "nil": false,
          "globalScope": false,
          "typeSubstituted": false
        },
        {
          "name": "CRITERES_D_ATTRIBUTION",
          "declaredType": "fr.gouv.dila.opendata.api.model.Boamp.Boamp_v110.Annonce$DONNEES$CRITERESDATTRIBUTION",
          "scope": "fr.gouv.dila.opendata.api.model.Boamp.Boamp_v110.Annonce$DONNEES",
          "value": {
            "titreandCRITERESCCTPAndLISTECRITERES": [
              {
                "name": "TITRE",
                "declaredType": "java.lang.String",
                "scope": "fr.gouv.dila.opendata.api.model.Boamp.Boamp_v110.Annonce$DONNEES$CRITERESDATTRIBUTION",
                "value": "Crit\u00e8res d'attribution retenus :",
                "nil": false,
                "globalScope": false,
                "typeSubstituted": false
              }
            ]
          },
          "nil": false,
          "globalScope": false,
          "typeSubstituted": false
        },
        {
          "name": "PROCEDURE",
          "declaredType": "fr.gouv.dila.opendata.api.model.Boamp.Boamp_v110.Procedure",
          "scope": "fr.gouv.dila.opendata.api.model.Boamp.Boamp_v110.Annonce$DONNEES",
          "value": {
            "type": "PROCEDURE_ADAPTEE",
            "titreandJUSTIFURGENCEAndAVIS12MOIS": [
              {
                "name": "AUTRES",
                "declaredType": "java.lang.String",
                "scope": "fr.gouv.dila.opendata.api.model.Boamp.Boamp_v110.Procedure",
                "value": ".",
                "nil": false,
                "globalScope": false,
                "typeSubstituted": false
              }
            ]
          },
          "nil": false,
          "globalScope": false,
          "typeSubstituted": false
        },
        {
          "name": "PROCEDURE",
          "declaredType": "fr.gouv.dila.opendata.api.model.Boamp.Boamp_v110.Procedure",
          "scope": "fr.gouv.dila.opendata.api.model.Boamp.Boamp_v110.Annonce$DONNEES",
          "value": {
            "type": null,
            "titreandJUSTIFURGENCEAndAVIS12MOIS": [
              {
                "name": "LOTS",
                "declaredType": "fr.gouv.dila.opendata.api.model.Boamp.Boamp_v110.Lot2",
                "scope": "fr.gouv.dila.opendata.api.model.Boamp.Boamp_v110.Procedure",
                "value": {
                  "titreandNUMLOTAndNOMENCLATURE": [
                    {
                      "name": "NUM_LOT",
                      "declaredType": "java.lang.String",
                      "scope": "fr.gouv.dila.opendata.api.model.Boamp.Boamp_v110.Lot2",
                      "value": "",
                      "nil": false,
                      "globalScope": false,
                      "typeSubstituted": false
                    },
                    {
                      "name": "DESC",
                      "declaredType": "java.lang.String",
                      "scope": "fr.gouv.dila.opendata.api.model.Boamp.Boamp_v110.Lot2",
                      "value": "mise \u00e0 disposition et maintenance de deux v\u00e9hicules d\u00e9givrage et antigivrage pour a\u00e9ronef sur la base a\u00e9rienne de Villacoublay pour une p\u00e9riode comprise entre le 6 octobre 2008 et le 6 mars 2009.",
                      "nil": false,
                      "globalScope": false,
                      "typeSubstituted": false
                    },
                    {
                      "name": "AUTRES",
                      "declaredType": "java.lang.String",
                      "scope": "fr.gouv.dila.opendata.api.model.Boamp.Boamp_v110.Lot2",
                      "value": "march\u00e9 n\u00b008 92 837.",
                      "nil": false,
                      "globalScope": false,
                      "typeSubstituted": false
                    },
                    {
                      "name": "NOM",
                      "declaredType": "java.lang.String",
                      "scope": "fr.gouv.dila.opendata.api.model.Boamp.Boamp_v110.Lot2",
                      "value": "AVIEX,",
                      "nil": false,
                      "globalScope": false,
                      "typeSubstituted": false
                    },
                    {
                      "name": "ADRESSE",
                      "declaredType": "java.lang.String",
                      "scope": "fr.gouv.dila.opendata.api.model.Boamp.Boamp_v110.Lot2",
                      "value": "13 rue Louis Bl\u00e9riot, ",
                      "nil": false,
                      "globalScope": false,
                      "typeSubstituted": false
                    },
                    {
                      "name": "CP",
                      "declaredType": "java.lang.String",
                      "scope": "fr.gouv.dila.opendata.api.model.Boamp.Boamp_v110.Lot2",
                      "value": "77290",
                      "nil": false,
                      "globalScope": false,
                      "typeSubstituted": false
                    },
                    {
                      "name": "VILLE",
                      "declaredType": "java.lang.String",
                      "scope": "fr.gouv.dila.opendata.api.model.Boamp.Boamp_v110.Lot2",
                      "value": "Compans.",
                      "nil": false,
                      "globalScope": false,
                      "typeSubstituted": false
                    },
                    {
                      "name": "MONTANT_HT",
                      "declaredType": "java.lang.String",
                      "scope": "fr.gouv.dila.opendata.api.model.Boamp.Boamp_v110.Lot2",
                      "value": "107 800,00 EUR.",
                      "nil": false,
                      "globalScope": false,
                      "typeSubstituted": false
                    },
                    {
                      "name": "DATE_ATT_MARCHE",
                      "declaredType": "java.lang.String",
                      "scope": "fr.gouv.dila.opendata.api.model.Boamp.Boamp_v110.Lot2",
                      "value": "15 septembre 2008",
                      "nil": false,
                      "globalScope": false,
                      "typeSubstituted": false
                    }
                  ]
                },
                "nil": false,
                "globalScope": false,
                "typeSubstituted": false
              },
              {
                "name": "AMP",
                "declaredType": "java.lang.Boolean",
                "scope": "fr.gouv.dila.opendata.api.model.Boamp.Boamp_v110.Procedure",
                "value": true,
                "nil": false,
                "globalScope": false,
                "typeSubstituted": false
              }
            ]
          },
          "nil": false,
          "globalScope": false,
          "typeSubstituted": false
        },
        {
          "name": "PROCEDURES_RECOURS",
          "declaredType": "fr.gouv.dila.opendata.api.model.Boamp.Boamp_v110.Annonce$DONNEES$PROCEDURESRECOURS",
          "scope": "fr.gouv.dila.opendata.api.model.Boamp.Boamp_v110.Annonce$DONNEES",
          "value": {
            "instancerecours": {
              "acheteurandNOMAndADRESSE": [
                {
                  "name": "ACHETEUR",
                  "declaredType": "java.lang.String",
                  "scope": "fr.gouv.dila.opendata.api.model.Boamp.Boamp_v110.ContactRecours",
                  "value": "Tribunal administratif de Versailles",
                  "nil": false,
                  "globalScope": false,
                  "typeSubstituted": false
                },
                {
                  "name": "ADRESSE",
                  "declaredType": "java.lang.String",
                  "scope": "fr.gouv.dila.opendata.api.model.Boamp.Boamp_v110.ContactRecours",
                  "value": "56 avenue de Saint-Cloud, ",
                  "nil": false,
                  "globalScope": false,
                  "typeSubstituted": false
                },
                {
                  "name": "CP",
                  "declaredType": "java.lang.String",
                  "scope": "fr.gouv.dila.opendata.api.model.Boamp.Boamp_v110.ContactRecours",
                  "value": "78000",
                  "nil": false,
                  "globalScope": false,
                  "typeSubstituted": false
                },
                {
                  "name": "VILLE",
                  "declaredType": "java.lang.String",
                  "scope": "fr.gouv.dila.opendata.api.model.Boamp.Boamp_v110.ContactRecours",
                  "value": "Versailles",
                  "nil": false,
                  "globalScope": false,
                  "typeSubstituted": false
                },
                {
                  "name": "AUTRES",
                  "declaredType": "java.lang.String",
                  "scope": "fr.gouv.dila.opendata.api.model.Boamp.Boamp_v110.ContactRecours",
                  "value": ".",
                  "nil": false,
                  "globalScope": false,
                  "typeSubstituted": false
                }
              ]
            },
            "organemediation": null,
            "rensrecours": null
          },
          "nil": false,
          "globalScope": false,
          "typeSubstituted": false
        },
        {
          "name": "PROCEDURES_RECOURS",
          "declaredType": "fr.gouv.dila.opendata.api.model.Boamp.Boamp_v110.Annonce$DONNEES$PROCEDURESRECOURS",
          "scope": "fr.gouv.dila.opendata.api.model.Boamp.Boamp_v110.Annonce$DONNEES",
          "value": {
            "instancerecours": null,
            "organemediation": null,
            "rensrecours": {
              "acheteurandNOMAndADRESSE": [
                {
                  "name": "ACHETEUR",
                  "declaredType": "java.lang.String",
                  "scope": "fr.gouv.dila.opendata.api.model.Boamp.Boamp_v110.ContactRecours",
                  "value": "Service des contrats et des finances",
                  "nil": false,
                  "globalScope": false,
                  "typeSubstituted": false
                },
                {
                  "name": "ADRESSE",
                  "declaredType": "java.lang.String",
                  "scope": "fr.gouv.dila.opendata.api.model.Boamp.Boamp_v110.ContactRecours",
                  "value": "simmad - base a\u00e9rienne 217, ",
                  "nil": false,
                  "globalScope": false,
                  "typeSubstituted": false
                },
                {
                  "name": "CP",
                  "declaredType": "java.lang.String",
                  "scope": "fr.gouv.dila.opendata.api.model.Boamp.Boamp_v110.ContactRecours",
                  "value": "91224",
                  "nil": false,
                  "globalScope": false,
                  "typeSubstituted": false
                },
                {
                  "name": "VILLE",
                  "declaredType": "java.lang.String",
                  "scope": "fr.gouv.dila.opendata.api.model.Boamp.Boamp_v110.ContactRecours",
                  "value": "Br\u00e9tigny-sur-Orge Cedex, ",
                  "nil": false,
                  "globalScope": false,
                  "typeSubstituted": false
                },
                {
                  "name": "TEL",
                  "declaredType": "java.lang.String",
                  "scope": "fr.gouv.dila.opendata.api.model.Boamp.Boamp_v110.ContactRecours",
                  "value": "01-69-23-87-06, ",
                  "nil": false,
                  "globalScope": false,
                  "typeSubstituted": false
                },
                {
                  "name": "MEL",
                  "declaredType": "java.lang.String",
                  "scope": "fr.gouv.dila.opendata.api.model.Boamp.Boamp_v110.ContactRecours",
                  "value": "scf.simmad@wanadoo.fr, ",
                  "nil": false,
                  "globalScope": false,
                  "typeSubstituted": false
                },
                {
                  "name": "FAX",
                  "declaredType": "java.lang.String",
                  "scope": "fr.gouv.dila.opendata.api.model.Boamp.Boamp_v110.ContactRecours",
                  "value": "01-69-23-86-60",
                  "nil": false,
                  "globalScope": false,
                  "typeSubstituted": false
                },
                {
                  "name": "AUTRES",
                  "declaredType": "java.lang.String",
                  "scope": "fr.gouv.dila.opendata.api.model.Boamp.Boamp_v110.ContactRecours",
                  "value": ".",
                  "nil": false,
                  "globalScope": false,
                  "typeSubstituted": false
                }
              ]
            }
          },
          "nil": false,
          "globalScope": false,
          "typeSubstituted": false
        },
        {
          "name": "PROCEDURE",
          "declaredType": "fr.gouv.dila.opendata.api.model.Boamp.Boamp_v110.Procedure",
          "scope": "fr.gouv.dila.opendata.api.model.Boamp.Boamp_v110.Annonce$DONNEES",
          "value": {
            "type": null,
            "titreandJUSTIFURGENCEAndAVIS12MOIS": [
              {
                "name": "DATE_ENVOI",
                "declaredType": "java.lang.String",
                "scope": "fr.gouv.dila.opendata.api.model.Boamp.Boamp_v110.Procedure",
                "value": "7 octobre 2008",
                "nil": false,
                "globalScope": false,
                "typeSubstituted": false
              }
            ]
          },
          "nil": false,
          "globalScope": false,
          "typeSubstituted": false
        },
        {
          "name": "CLASSES",
          "declaredType": "fr.gouv.dila.opendata.api.model.Boamp.Boamp_v110.Classes",
          "scope": "fr.gouv.dila.opendata.api.model.Boamp.Boamp_v110.Annonce$DONNEES",
          "value": {
            "classe": [
              "Produits de l'industrie automobile",
              "Services fournis principalement aux entreprises"
            ]
          },
          "nil": false,
          "globalScope": false,
          "typeSubstituted": false
        },
        {
          "name": "DESCRIPTEURS",
          "declaredType": "fr.gouv.dila.opendata.api.model.Boamp.Boamp_v110.Annonce$DONNEES$DESCRIPTEURS",
          "scope": "fr.gouv.dila.opendata.api.model.Boamp.Boamp_v110.Annonce$DONNEES",
          "value": {
            "descripteur": [
              "Maintenance",
              "V\u00e9hicules"
            ]
          },
          "nil": false,
          "globalScope": false,
          "typeSubstituted": false
        },
        {
          "name": "AUTRES",
          "declaredType": "java.lang.String",
          "scope": "fr.gouv.dila.opendata.api.model.Boamp.Boamp_v110.Annonce$DONNEES",
          "value": "78 mise \u00e0 disposition et maintenance de deux v\u00e9hicules d\u00e9givrage et antigivrage pour a\u00e9ronef sur la base a\u00e9rienne de villacoublay",
          "nil": false,
          "globalScope": false,
          "typeSubstituted": false
        }
      ]
    }
  },
  "nompublication": "BOMP C",
  "dateparution": "13 octobre 2008",
  "numparution": "20080082"
}