{
  "annonce": {
    "gestion": {
      "nojo": "08-224866",
      "rappel": null,
      "r2": "40",
      "r3": "91",
      "tetierr3": "91 - Essonne",
      "r4": "6",
      "tetierr4": "Avis d'attribution",
      "k1": null,
      "doublon": null,
      "k9": null,
      "numann": "330",
      "nomhtml": "/2008/MPC/MPC20080078/200809290330C.HTM"
    },
    "donnees": {
      "titreandINFOAndTYPEACTIVITEORG": [
        {
          "name": "IDENT",
          "declaredType": "fr.gouv.dila.opendata.api.model.Boamp.Boamp_v110.Identite",
          "scope": "fr.gouv.dila.opendata.api.model.Boamp.Boamp_v110.Annonce$DONNEES",
          "value": {
            "titreandNOMAndCODEIDENTNATIONAL": [
              {
                "name": "NOM",
                "declaredType": "java.lang.String",
                "scope": "fr.gouv.dila.opendata.api.model.Boamp.Boamp_v110.Identite",
                "value": "Ville de Villebon-sur-Yvette",
                "nil": false,
                "globalScope": false,
                "typeSubstituted": false
              },
              {
                "name": "ADRESSE",
                "declaredType": "java.lang.String",
                "scope": "fr.gouv.dila.opendata.api.model.Boamp.Boamp_v110.Identite",
                "value": "centre technique municipal rue du commandant Marin-La-Mesl\u00e9e",
                "nil": false,
                "globalScope": false,
                "typeSubstituted": false
              },
              {
                "name": "CP",
                "declaredType": "java.lang.String",
                "scope": "fr.gouv.dila.opendata.api.model.Boamp.Boamp_v110.Identite",
                "value": "91140",
                "nil": false,
                "globalScope": false,
                "typeSubstituted": false
              },
              {
                "name": "VILLE",
                "declaredType": "java.lang.String",
                "scope": "fr.gouv.dila.opendata.api.model.Boamp.Boamp_v110.Identite",
                "value": "Villebon-sur-Yvette",
                "nil": false,
                "globalScope": false,
                "typeSubstituted": false
              }
            ]
          },
          "nil": false,
          "globalScope": false,
          "typeSubstituted": false
        },
        {
          "name": "PROCEDURE",
          "declaredType": "fr.gouv.dila.opendata.api.model.Boamp.Boamp_v110.Procedure",
          "scope": "fr.gouv.dila.opendata.api.model.Boamp.Boamp_v110.Annonce$DONNEES",
          "value": {
            "type": "RESTREINT",
            "titreandJUSTIFURGENCEAndAVIS12MOIS": []
          },
          "nil": false,
          "globalScope": false,
          "typeSubstituted": false
        },
        {
          "name": "IDENT",
          "declaredType": "fr.gouv.dila.opendata.api.model.Boamp.Boamp_v110.Identite",
          "scope": "fr.gouv.dila.opendata.api.model.Boamp.Boamp_v110.Annonce$DONNEES",
          "value": {
            "titreandNOMAndCODEIDENTNATIONAL": [
              {
                "name": "NOM",
                "declaredType": "java.lang.String",
                "scope": "fr.gouv.dila.opendata.api.model.Boamp.Boamp_v110.Identite",
                "value": "Europe service voirie, ",
                "nil": false,
                "globalScope": false,
                "typeSubstituted": false
              },
              {
                "name": "ADRESSE",
                "declaredType": "java.lang.String",
                "scope": "fr.gouv.dila.opendata.api.model.Boamp.Boamp_v110.Identite",
                "value": "Le parc de viry1 rue de ris, ",
                "nil": false,
                "globalScope": false,
                "typeSubstituted": false
              },
              {
                "name": "CP",
                "declaredType": "java.lang.String",
                "scope": "fr.gouv.dila.opendata.api.model.Boamp.Boamp_v110.Identite",
                "value": "91170",
                "nil": false,
                "globalScope": false,
                "typeSubstituted": false
              },
              {
                "name": "VILLE",
                "declaredType": "java.lang.String",
                "scope": "fr.gouv.dila.opendata.api.model.Boamp.Boamp_v110.Identite",
                "value": "Viry chatillon.",
                "nil": false,
                "globalScope": false,
                "typeSubstituted": false
              }
            ]
          },
          "nil": false,
          "globalScope": false,
          "typeSubstituted": false
        },
        {
          "name": "IDENT",
          "declaredType": "fr.gouv.dila.opendata.api.model.Boamp.Boamp_v110.Identite",
          "scope": "fr.gouv.dila.opendata.api.model.Boamp.Boamp_v110.Annonce$DONNEES",
          "value": {
            "titreandNOMAndCODEIDENTNATIONAL": [
              {
                "name": "NOM",
                "declaredType": "java.lang.String",
                "scope": "fr.gouv.dila.opendata.api.model.Boamp.Boamp_v110.Identite",
                "value": "Europe Service Voirie, ",
                "nil": false,
                "globalScope": false,
                "typeSubstituted": false
              },
              {
                "name": "ADRESSE",
                "declaredType": "java.lang.String",
                "scope": "fr.gouv.dila.opendata.api.model.Boamp.Boamp_v110.Identite",
                "value": "Le parc de viry1 rue de Ris, ",
                "nil": false,
                "globalScope": false,
                "typeSubstituted": false
              },
              {
                "name": "CP",
                "declaredType": "java.lang.String",
                "scope": "fr.gouv.dila.opendata.api.model.Boamp.Boamp_v110.Identite",
                "value": "91170",
                "nil": false,
                "globalScope": false,
                "typeSubstituted": false
              },
              {
                "name": "VILLE",
                "declaredType": "java.lang.String",
                "scope": "fr.gouv.dila.opendata.api.model.Boamp.Boamp_v110.Identite",
                "value": "viry chatillon.",
                "nil": false,
                "globalScope": false,
                "typeSubstituted": false
              }
            ]
          },
          "nil": false,
          "globalScope": false,
          "typeSubstituted": false
        },
        {
          "name": "INFO",
          "declaredType": "fr.gouv.dila.opendata.api.model.Boamp.Boamp_v110.Info",
          "scope": "fr.gouv.dila.opendata.api.model.Boamp.Boamp_v110.Annonce$DONNEES",
          "value": {
            "travauxandFOURNITURESAndSERVICES": [
              {
                "name": "PUBLICATIONS",
                "declaredType": "fr.gouv.dila.opendata.api.model.Boamp.Boamp_v110.Info$PUBLICATIONS",
                "scope": "fr.gouv.dila.opendata.api.model.Boamp.Boamp_v110.Info",
                "value": {
                  "publication": [
                    {
                      "parutionandEDITIONAndANNONCE": [
                        {
                          "name": "PARUTION",
                          "declaredType": "java.lang.String",
                          "scope": "fr.gouv.dila.opendata.api.model.Boamp.Boamp_v110.Info$PUBLICATIONS$PUBLICATION",
                          "value": "7 A",
                          "nil": false,
                          "globalScope": false,
                          "typeSubstituted": false
                        },
                        {
                          "name": "ANNONCE",
                          "declaredType": "java.lang.String",
                          "scope": "fr.gouv.dila.opendata.api.model.Boamp.Boamp_v110.Info$PUBLICATIONS$PUBLICATION",
                          "value": "154",
                          "nil": false,
                          "globalScope": false,
                          "typeSubstituted": false
                        },
                        {
                          "name": "DATE",
                          "declaredType": "java.lang.String",
                          "scope": "fr.gouv.dila.opendata.api.model.Boamp.Boamp_v110.Info$PUBLICATIONS$PUBLICATION",
                          "value": "10 janvier 2008",
                          "nil": false,
                          "globalScope": false,
                          "typeSubstituted": false
                        }
                      ]
                    }
                  ]
                },
                "nil": false,
                "globalScope": false,
                "typeSubstituted": false
              }
            ]
          },
          "nil": false,
          "globalScope": false,
          "typeSubstituted": false
        },
        {
          "name": "CLASSES",
          "declaredType": "fr.gouv.dila.opendata.api.model.Boamp.Boamp_v110.Classes",
          "scope": "fr.gouv.dila.opendata.api.model.Boamp.Boamp_v110.Annonce$DONNEES",
          "value": {
            "classe": [
              "Assainissement, voirie et gestion des d\u00e9chets"
            ]
          },
          "nil": false,
          "globalScope": false,
          "typeSubstituted": false
        },
        {
          "name": "DESCRIPTEURS",
          "declaredType": "fr.gouv.dila.opendata.api.model.Boamp.Boamp_v110.Annonce$DONNEES$DESCRIPTEURS",
          "scope": "fr.gouv.dila.opendata.api.model.Boamp.Boamp_v110.Annonce$DONNEES",
          "value": {
            "descripteur": [
              "Ordures m\u00e9nag\u00e8res (prestations)"
            ]
          },
          "nil": false,
          "globalScope": false,
          "typeSubstituted": false
        },
        {
          "name": "AUTRES",
          "declaredType": "java.lang.String",
          "scope": "fr.gouv.dila.opendata.api.model.Boamp.Boamp_v110.Annonce$DONNEES",
          "value": "91 march\u00e9 de balayage des voies communales \u00e0 Villebon-Sur-Yvette",
          "nil": false,
          "globalScope": false,
          "typeSubstituted": false
        }
      ]
    }
  },
  "nompublication": "BOMP C",
  "dateparution": "29 septembre 2008",
  "numparution": "20080078"
}