{
  "annonce": {
    "gestion": {
      "nojo": "08-263080",
      "rappel": null,
      "r2": "4",
      "r3": "83",
      "tetierr3": "83 - Var",
      "r4": "9",
      "tetierr4": "Avis d'attribution",
      "k1": null,
      "doublon": null,
      "k9": null,
      "numann": "193",
      "nomhtml": "/2008/MPC/MPC20080095/200811270193C.HTM"
    },
    "donnees": {
      "titreandINFOAndTYPEACTIVITEORG": [
        {
          "name": "INFO",
          "declaredType": "fr.gouv.dila.opendata.api.model.Boamp.Boamp_v110.Info",
          "scope": "fr.gouv.dila.opendata.api.model.Boamp.Boamp_v110.Annonce$DONNEES",
          "value": {
            "travauxandFOURNITURESAndSERVICES": [
              {
                "name": "ETAT",
                "declaredType": "java.lang.String",
                "scope": "fr.gouv.dila.opendata.api.model.Boamp.Boamp_v110.Info",
                "value": "",
                "nil": false,
                "globalScope": false,
                "typeSubstituted": false
              }
            ]
          },
          "nil": false,
          "globalScope": false,
          "typeSubstituted": false
        },
        {
          "name": "IDENT",
          "declaredType": "fr.gouv.dila.opendata.api.model.Boamp.Boamp_v110.Identite",
          "scope": "fr.gouv.dila.opendata.api.model.Boamp.Boamp_v110.Annonce$DONNEES",
          "value": {
            "titreandNOMAndCODEIDENTNATIONAL": [
              {
                "name": "TITRE",
                "declaredType": "java.lang.String",
                "scope": "fr.gouv.dila.opendata.api.model.Boamp.Boamp_v110.Identite",
                "value": "Nom et adresse officiels de l'organisme acheteur : ",
                "nil": false,
                "globalScope": false,
                "typeSubstituted": false
              },
              {
                "name": "NOM",
                "declaredType": "java.lang.String",
                "scope": "fr.gouv.dila.opendata.api.model.Boamp.Boamp_v110.Identite",
                "value": "MINDEF/Dga/Det/Ctsn.",
                "nil": false,
                "globalScope": false,
                "typeSubstituted": false
              },
              {
                "name": "PRM",
                "declaredType": "java.lang.String",
                "scope": "fr.gouv.dila.opendata.api.model.Boamp.Boamp_v110.Identite",
                "value": "mindef / dga / det / ctsn,",
                "nil": false,
                "globalScope": false,
                "typeSubstituted": false
              },
              {
                "name": "ADRESSE",
                "declaredType": "java.lang.String",
                "scope": "fr.gouv.dila.opendata.api.model.Boamp.Boamp_v110.Identite",
                "value": "avenue de la tour royale B.P. 40915, ",
                "nil": false,
                "globalScope": false,
                "typeSubstituted": false
              },
              {
                "name": "CP",
                "declaredType": "java.lang.String",
                "scope": "fr.gouv.dila.opendata.api.model.Boamp.Boamp_v110.Identite",
                "value": "83050",
                "nil": false,
                "globalScope": false,
                "typeSubstituted": false
              },
              {
                "name": "VILLE",
                "declaredType": "java.lang.String",
                "scope": "fr.gouv.dila.opendata.api.model.Boamp.Boamp_v110.Identite",
                "value": "Toulon Cedex, ",
                "nil": false,
                "globalScope": false,
                "typeSubstituted": false
              },
              {
                "name": "MEL",
                "declaredType": "java.lang.String",
                "scope": "fr.gouv.dila.opendata.api.model.Boamp.Boamp_v110.Identite",
                "value": "dgactsn.bao@laposte.net.",
                "nil": false,
                "globalScope": false,
                "typeSubstituted": false
              },
              {
                "name": "AGIT_POUR_AUTRE_COMPTE",
                "declaredType": "java.lang.Boolean",
                "scope": "fr.gouv.dila.opendata.api.model.Boamp.Boamp_v110.Identite",
                "value": false,
                "nil": false,
                "globalScope": false,
                "typeSubstituted": false
              }
            ]
          },
          "nil": false,
          "globalScope": false,
          "typeSubstituted": false
        },
        {
          "name": "TYPE_ACTIVITE_ORG",
          "declaredType": "fr.gouv.dila.opendata.api.model.Boamp.Boamp_v110.EnumActiviteOrganisationnelle",
          "scope": "fr.gouv.dila.opendata.api.model.Boamp.Boamp_v110.Annonce$DONNEES",
          "value": {
            "pouvoiradjudicateurandENTITEADJUDICATRICEAndACTSERVADMPUB": [
              {
                "name": "POUVOIR_ADJUDICATEUR",
                "declaredType": "java.lang.String",
                "scope": "fr.gouv.dila.opendata.api.model.Boamp.Boamp_v110.EnumActiviteOrganisationnelle",
                "value": "",
                "nil": false,
                "globalScope": false,
                "typeSubstituted": false
              },
              {
                "name": "DEF",
                "declaredType": "java.lang.String",
                "scope": "fr.gouv.dila.opendata.api.model.Boamp.Boamp_v110.EnumActiviteOrganisationnelle",
                "value": "",
                "nil": false,
                "globalScope": false,
                "typeSubstituted": false
              }
            ]
          },
          "nil": false,
          "globalScope": false,
          "typeSubstituted": false
        },
        {
          "name": "OBJET",
          "declaredType": "fr.gouv.dila.opendata.api.model.Boamp.Boamp_v110.Objet",
          "scope": "fr.gouv.dila.opendata.api.model.Boamp.Boamp_v110.Annonce$DONNEES",
          "value": {
            "titreandOBJETCOMPLETAndTITREMARCHE": [
              {
                "name": "TITRE",
                "declaredType": "java.lang.String",
                "scope": "fr.gouv.dila.opendata.api.model.Boamp.Boamp_v110.Objet",
                "value": "Objet du march\u00e9 :",
                "nil": false,
                "globalScope": false,
                "typeSubstituted": false
              },
              {
                "name": "OBJET_COMPLET",
                "declaredType": "java.lang.String",
                "scope": "fr.gouv.dila.opendata.api.model.Boamp.Boamp_v110.Objet",
                "value": "acquisition de mat\u00e9riels pour la s\u00e9curisation de liaison Ist/Pipady/Mourillon.",
                "nil": false,
                "globalScope": false,
                "typeSubstituted": false
              },
              {
                "name": "ACHAT",
                "declaredType": "java.lang.String",
                "scope": "fr.gouv.dila.opendata.api.model.Boamp.Boamp_v110.Objet",
                "value": "",
                "nil": false,
                "globalScope": false,
                "typeSubstituted": false
              },
              {
                "name": "LIEU_LIVR",
                "declaredType": "java.lang.String",
                "scope": "fr.gouv.dila.opendata.api.model.Boamp.Boamp_v110.Objet",
                "value": "minist\u00e8re de la d\u00e9fense / dga / ctsn, 83050 Toulon Cedex.",
                "nil": false,
                "globalScope": false,
                "typeSubstituted": false
              },
              {
                "name": "CODE_NUTS",
                "declaredType": "java.lang.String",
                "scope": "fr.gouv.dila.opendata.api.model.Boamp.Boamp_v110.Objet",
                "value": "FR825.",
                "nil": false,
                "globalScope": false,
                "typeSubstituted": false
              },
              {
                "name": "CPV_OBJ",
                "declaredType": "java.lang.String",
                "scope": "fr.gouv.dila.opendata.api.model.Boamp.Boamp_v110.Objet",
                "value": "35000000.",
                "nil": false,
                "globalScope": false,
                "typeSubstituted": false
              }
            ]
          },
          "nil": false,
          "globalScope": false,
          "typeSubstituted": false
        },
        {
          "name": "PROCEDURE",
          "declaredType": "fr.gouv.dila.opendata.api.model.Boamp.Boamp_v110.Procedure",
          "scope": "fr.gouv.dila.opendata.api.model.Boamp.Boamp_v110.Annonce$DONNEES",
          "value": {
            "type": "MARCHE_NEGOCIE",
            "titreandJUSTIFURGENCEAndAVIS12MOIS": [
              {
                "name": "AUTRES",
                "declaredType": "java.lang.String",
                "scope": "fr.gouv.dila.opendata.api.model.Boamp.Boamp_v110.Procedure",
                "value": ".",
                "nil": false,
                "globalScope": false,
                "typeSubstituted": false
              },
              {
                "name": "VALEUR_ESTIMEE",
                "declaredType": "fr.gouv.dila.opendata.api.model.Boamp.Boamp_v110.Procedure$VALEURESTIMEE",
                "scope": "fr.gouv.dila.opendata.api.model.Boamp.Boamp_v110.Procedure",
                "value": {
                  "value": "38 462,71 EUR",
                  "type": "HT"
                },
                "nil": false,
                "globalScope": false,
                "typeSubstituted": false
              }
            ]
          },
          "nil": false,
          "globalScope": false,
          "typeSubstituted": false
        },
        {
          "name": "PROCEDURE",
          "declaredType": "fr.gouv.dila.opendata.api.model.Boamp.Boamp_v110.Procedure",
          "scope": "fr.gouv.dila.opendata.api.model.Boamp.Boamp_v110.Annonce$DONNEES",
          "value": {
            "type": null,
            "titreandJUSTIFURGENCEAndAVIS12MOIS": [
              {
                "name": "LOTS",
                "declaredType": "fr.gouv.dila.opendata.api.model.Boamp.Boamp_v110.Lot2",
                "scope": "fr.gouv.dila.opendata.api.model.Boamp.Boamp_v110.Procedure",
                "value": {
                  "titreandNUMLOTAndNOMENCLATURE": [
                    {
                      "name": "NUM_LOT",
                      "declaredType": "java.lang.String",
                      "scope": "fr.gouv.dila.opendata.api.model.Boamp.Boamp_v110.Lot2",
                      "value": "",
                      "nil": false,
                      "globalScope": false,
                      "typeSubstituted": false
                    },
                    {
                      "name": "NUM_LOT",
                      "declaredType": "java.lang.String",
                      "scope": "fr.gouv.dila.opendata.api.model.Boamp.Boamp_v110.Lot2",
                      "value": "2007 61 143",
                      "nil": false,
                      "globalScope": false,
                      "typeSubstituted": false
                    },
                    {
                      "name": "DESC",
                      "declaredType": "java.lang.String",
                      "scope": "fr.gouv.dila.opendata.api.model.Boamp.Boamp_v110.Lot2",
                      "value": "acquisition de mat\u00e9riels pour la s\u00e9curisation de liaison Ist/Pipady/Mourillon.",
                      "nil": false,
                      "globalScope": false,
                      "typeSubstituted": false
                    },
                    {
                      "name": "NOM",
                      "declaredType": "java.lang.String",
                      "scope": "fr.gouv.dila.opendata.api.model.Boamp.Boamp_v110.Lot2",
                      "value": "Thales communications,",
                      "nil": false,
                      "globalScope": false,
                      "typeSubstituted": false
                    },
                    {
                      "name": "ADRESSE",
                      "declaredType": "java.lang.String",
                      "scope": "fr.gouv.dila.opendata.api.model.Boamp.Boamp_v110.Lot2",
                      "value": "160 boulevard de Valmy B.P. 82, ",
                      "nil": false,
                      "globalScope": false,
                      "typeSubstituted": false
                    },
                    {
                      "name": "CP",
                      "declaredType": "java.lang.String",
                      "scope": "fr.gouv.dila.opendata.api.model.Boamp.Boamp_v110.Lot2",
                      "value": "92704",
                      "nil": false,
                      "globalScope": false,
                      "typeSubstituted": false
                    },
                    {
                      "name": "VILLE",
                      "declaredType": "java.lang.String",
                      "scope": "fr.gouv.dila.opendata.api.model.Boamp.Boamp_v110.Lot2",
                      "value": "Colombes Cedex.",
                      "nil": false,
                      "globalScope": false,
                      "typeSubstituted": false
                    },
                    {
                      "name": "MONTANT_HT",
                      "declaredType": "java.lang.String",
                      "scope": "fr.gouv.dila.opendata.api.model.Boamp.Boamp_v110.Lot2",
                      "value": "38 462,71 EUR.",
                      "nil": false,
                      "globalScope": false,
                      "typeSubstituted": false
                    },
                    {
                      "name": "DATE_ATT_MARCHE",
                      "declaredType": "java.lang.String",
                      "scope": "fr.gouv.dila.opendata.api.model.Boamp.Boamp_v110.Lot2",
                      "value": "20 octobre 2008",
                      "nil": false,
                      "globalScope": false,
                      "typeSubstituted": false
                    },
                    {
                      "name": "NB_OFFRES",
                      "declaredType": "java.lang.String",
                      "scope": "fr.gouv.dila.opendata.api.model.Boamp.Boamp_v110.Lot2",
                      "value": "1",
                      "nil": false,
                      "globalScope": false,
                      "typeSubstituted": false
                    }
                  ]
                },
                "nil": false,
                "globalScope": false,
                "typeSubstituted": false
              },
              {
                "name": "AMP",
                "declaredType": "java.lang.Boolean",
                "scope": "fr.gouv.dila.opendata.api.model.Boamp.Boamp_v110.Procedure",
                "value": true,
                "nil": false,
                "globalScope": false,
                "typeSubstituted": false
              }
            ]
          },
          "nil": false,
          "globalScope": false,
          "typeSubstituted": false
        },
        {
          "name": "PROCEDURES_RECOURS",
          "declaredType": "fr.gouv.dila.opendata.api.model.Boamp.Boamp_v110.Annonce$DONNEES$PROCEDURESRECOURS",
          "scope": "fr.gouv.dila.opendata.api.model.Boamp.Boamp_v110.Annonce$DONNEES",
          "value": {
            "instancerecours": {
              "acheteurandNOMAndADRESSE": [
                {
                  "name": "ACHETEUR",
                  "declaredType": "java.lang.String",
                  "scope": "fr.gouv.dila.opendata.api.model.Boamp.Boamp_v110.ContactRecours",
                  "value": "Tribunal administratif de Toulon",
                  "nil": false,
                  "globalScope": false,
                  "typeSubstituted": false
                },
                {
                  "name": "ADRESSE",
                  "declaredType": "java.lang.String",
                  "scope": "fr.gouv.dila.opendata.api.model.Boamp.Boamp_v110.ContactRecours",
                  "value": "5 rue Racine B.P. 40510, ",
                  "nil": false,
                  "globalScope": false,
                  "typeSubstituted": false
                },
                {
                  "name": "CP",
                  "declaredType": "java.lang.String",
                  "scope": "fr.gouv.dila.opendata.api.model.Boamp.Boamp_v110.ContactRecours",
                  "value": "83041",
                  "nil": false,
                  "globalScope": false,
                  "typeSubstituted": false
                },
                {
                  "name": "VILLE",
                  "declaredType": "java.lang.String",
                  "scope": "fr.gouv.dila.opendata.api.model.Boamp.Boamp_v110.ContactRecours",
                  "value": "Toulon, ",
                  "nil": false,
                  "globalScope": false,
                  "typeSubstituted": false
                },
                {
                  "name": "TEL",
                  "declaredType": "java.lang.String",
                  "scope": "fr.gouv.dila.opendata.api.model.Boamp.Boamp_v110.ContactRecours",
                  "value": "04-94-42-79-30, ",
                  "nil": false,
                  "globalScope": false,
                  "typeSubstituted": false
                },
                {
                  "name": "MEL",
                  "declaredType": "java.lang.String",
                  "scope": "fr.gouv.dila.opendata.api.model.Boamp.Boamp_v110.ContactRecours",
                  "value": "greffe.ta-toulon@juradm.fr, ",
                  "nil": false,
                  "globalScope": false,
                  "typeSubstituted": false
                },
                {
                  "name": "FAX",
                  "declaredType": "java.lang.String",
                  "scope": "fr.gouv.dila.opendata.api.model.Boamp.Boamp_v110.ContactRecours",
                  "value": "04-94-42-79-89",
                  "nil": false,
                  "globalScope": false,
                  "typeSubstituted": false
                },
                {
                  "name": "AUTRES",
                  "declaredType": "java.lang.String",
                  "scope": "fr.gouv.dila.opendata.api.model.Boamp.Boamp_v110.ContactRecours",
                  "value": ".",
                  "nil": false,
                  "globalScope": false,
                  "typeSubstituted": false
                }
              ]
            },
            "organemediation": null,
            "rensrecours": null
          },
          "nil": false,
          "globalScope": false,
          "typeSubstituted": false
        },
        {
          "name": "PROCEDURES_RECOURS",
          "declaredType": "fr.gouv.dila.opendata.api.model.Boamp.Boamp_v110.Annonce$DONNEES$PROCEDURESRECOURS",
          "scope": "fr.gouv.dila.opendata.api.model.Boamp.Boamp_v110.Annonce$DONNEES",
          "value": {
            "instancerecours": null,
            "organemediation": null,
            "rensrecours": {
              "acheteurandNOMAndADRESSE": [
                {
                  "name": "ACHETEUR",
                  "declaredType": "java.lang.String",
                  "scope": "fr.gouv.dila.opendata.api.model.Boamp.Boamp_v110.ContactRecours",
                  "value": "Minist\u00e8re de la d\u00e9fense / DGA / CTSN / SDAF / DMA",
                  "nil": false,
                  "globalScope": false,
                  "typeSubstituted": false
                },
                {
                  "name": "ADRESSE",
                  "declaredType": "java.lang.String",
                  "scope": "fr.gouv.dila.opendata.api.model.Boamp.Boamp_v110.ContactRecours",
                  "value": "avenue de la Tour Royale - B.P. 40 915, ",
                  "nil": false,
                  "globalScope": false,
                  "typeSubstituted": false
                },
                {
                  "name": "CP",
                  "declaredType": "java.lang.String",
                  "scope": "fr.gouv.dila.opendata.api.model.Boamp.Boamp_v110.ContactRecours",
                  "value": "83050",
                  "nil": false,
                  "globalScope": false,
                  "typeSubstituted": false
                },
                {
                  "name": "VILLE",
                  "declaredType": "java.lang.String",
                  "scope": "fr.gouv.dila.opendata.api.model.Boamp.Boamp_v110.ContactRecours",
                  "value": "Toulon Cedex, ",
                  "nil": false,
                  "globalScope": false,
                  "typeSubstituted": false
                },
                {
                  "name": "MEL",
                  "declaredType": "java.lang.String",
                  "scope": "fr.gouv.dila.opendata.api.model.Boamp.Boamp_v110.ContactRecours",
                  "value": "thierry.mas-saint-guiral@dga.defense.gouv.fr, ",
                  "nil": false,
                  "globalScope": false,
                  "typeSubstituted": false
                },
                {
                  "name": "FAX",
                  "declaredType": "java.lang.String",
                  "scope": "fr.gouv.dila.opendata.api.model.Boamp.Boamp_v110.ContactRecours",
                  "value": "04-94-02-02-45",
                  "nil": false,
                  "globalScope": false,
                  "typeSubstituted": false
                },
                {
                  "name": "AUTRES",
                  "declaredType": "java.lang.String",
                  "scope": "fr.gouv.dila.opendata.api.model.Boamp.Boamp_v110.ContactRecours",
                  "value": ".",
                  "nil": false,
                  "globalScope": false,
                  "typeSubstituted": false
                }
              ]
            }
          },
          "nil": false,
          "globalScope": false,
          "typeSubstituted": false
        },
        {
          "name": "PROCEDURE",
          "declaredType": "fr.gouv.dila.opendata.api.model.Boamp.Boamp_v110.Procedure",
          "scope": "fr.gouv.dila.opendata.api.model.Boamp.Boamp_v110.Annonce$DONNEES",
          "value": {
            "type": null,
            "titreandJUSTIFURGENCEAndAVIS12MOIS": [
              {
                "name": "DATE_ENVOI",
                "declaredType": "java.lang.String",
                "scope": "fr.gouv.dila.opendata.api.model.Boamp.Boamp_v110.Procedure",
                "value": "4 novembre 2008",
                "nil": false,
                "globalScope": false,
                "typeSubstituted": false
              }
            ]
          },
          "nil": false,
          "globalScope": false,
          "typeSubstituted": false
        },
        {
          "name": "ANNEXE_1",
          "declaredType": "fr.gouv.dila.opendata.api.model.Boamp.Boamp_v110.Annexe1",
          "scope": "fr.gouv.dila.opendata.api.model.Boamp.Boamp_v110.Annonce$DONNEES",
          "value": {
            "titreandRECHERCHEAndURGENCEIMPERIEUSE": [
              {
                "name": "TITRE",
                "declaredType": "java.lang.String",
                "scope": "fr.gouv.dila.opendata.api.model.Boamp.Boamp_v110.Annexe1",
                "value": " Justification du recours \u00e0 la proc\u00e9dure n\u00e9goci\u00e9e sans publicit\u00e9 pr\u00e9alable et/ou sans mise en concurrence (articles 35 et 144 du code des march\u00e9s publics) :",
                "nil": false,
                "globalScope": false,
                "typeSubstituted": false
              },
              {
                "name": "PROT_DROITS",
                "declaredType": "java.lang.String",
                "scope": "fr.gouv.dila.opendata.api.model.Boamp.Boamp_v110.Annexe1",
                "value": "",
                "nil": false,
                "globalScope": false,
                "typeSubstituted": false
              }
            ]
          },
          "nil": false,
          "globalScope": false,
          "typeSubstituted": false
        },
        {
          "name": "CLASSES",
          "declaredType": "fr.gouv.dila.opendata.api.model.Boamp.Boamp_v110.Classes",
          "scope": "fr.gouv.dila.opendata.api.model.Boamp.Boamp_v110.Annonce$DONNEES",
          "value": {
            "classe": [
              "Machines et \u00e9quipements",
              "Autres mat\u00e9riels de transport"
            ]
          },
          "nil": false,
          "globalScope": false,
          "typeSubstituted": false
        },
        {
          "name": "DESCRIPTEURS",
          "declaredType": "fr.gouv.dila.opendata.api.model.Boamp.Boamp_v110.Annonce$DONNEES$DESCRIPTEURS",
          "scope": "fr.gouv.dila.opendata.api.model.Boamp.Boamp_v110.Annonce$DONNEES",
          "value": {
            "descripteur": [
              "Mat\u00e9riel de secours et d'incendie"
            ]
          },
          "nil": false,
          "globalScope": false,
          "typeSubstituted": false
        },
        {
          "name": "AUTRES",
          "declaredType": "java.lang.String",
          "scope": "fr.gouv.dila.opendata.api.model.Boamp.Boamp_v110.Annonce$DONNEES",
          "value": "83 Acquisition de mat\u00e9riels pour la s\u00e9curisation de liaison ist/pipady/mourillon",
          "nil": false,
          "globalScope": false,
          "typeSubstituted": false
        }
      ]
    }
  },
  "nompublication": "BOMP C",
  "dateparution": "27 novembre 2008",
  "numparution": "20080095"
}