{
  "annonce": {
    "gestion": {
      "nojo": "08-215642",
      "rappel": null,
      "r2": "40",
      "r3": "1",
      "tetierr3": "01 - Ain",
      "r4": "6",
      "tetierr4": "Avis d'attribution",
      "k1": null,
      "doublon": null,
      "k9": null,
      "numann": "238",
      "nomhtml": "/2008/MPC/MPC20080075/200809180238C.HTM"
    },
    "donnees": {
      "titreandINFOAndTYPEACTIVITEORG": [
        {
          "name": "IDENT",
          "declaredType": "fr.gouv.dila.opendata.api.model.Boamp.Boamp_v110.Identite",
          "scope": "fr.gouv.dila.opendata.api.model.Boamp.Boamp_v110.Annonce$DONNEES",
          "value": {
            "titreandNOMAndCODEIDENTNATIONAL": [
              {
                "name": "NOM",
                "declaredType": "java.lang.String",
                "scope": "fr.gouv.dila.opendata.api.model.Boamp.Boamp_v110.Identite",
                "value": "conseil g\u00e9n\u00e9ral de l'Ain",
                "nil": false,
                "globalScope": false,
                "typeSubstituted": false
              },
              {
                "name": "ADRESSE",
                "declaredType": "java.lang.String",
                "scope": "fr.gouv.dila.opendata.api.model.Boamp.Boamp_v110.Identite",
                "value": "service travaux neufs 21 rue Bourgmayer",
                "nil": false,
                "globalScope": false,
                "typeSubstituted": false
              },
              {
                "name": "CP",
                "declaredType": "java.lang.String",
                "scope": "fr.gouv.dila.opendata.api.model.Boamp.Boamp_v110.Identite",
                "value": "01000",
                "nil": false,
                "globalScope": false,
                "typeSubstituted": false
              },
              {
                "name": "VILLE",
                "declaredType": "java.lang.String",
                "scope": "fr.gouv.dila.opendata.api.model.Boamp.Boamp_v110.Identite",
                "value": "Bourg-en-Bresse.",
                "nil": false,
                "globalScope": false,
                "typeSubstituted": false
              }
            ]
          },
          "nil": false,
          "globalScope": false,
          "typeSubstituted": false
        },
        {
          "name": "PROCEDURE",
          "declaredType": "fr.gouv.dila.opendata.api.model.Boamp.Boamp_v110.Procedure",
          "scope": "fr.gouv.dila.opendata.api.model.Boamp.Boamp_v110.Annonce$DONNEES",
          "value": {
            "type": "OUVERT",
            "titreandJUSTIFURGENCEAndAVIS12MOIS": []
          },
          "nil": false,
          "globalScope": false,
          "typeSubstituted": false
        },
        {
          "name": "IDENT",
          "declaredType": "fr.gouv.dila.opendata.api.model.Boamp.Boamp_v110.Identite",
          "scope": "fr.gouv.dila.opendata.api.model.Boamp.Boamp_v110.Annonce$DONNEES",
          "value": {
            "titreandNOMAndCODEIDENTNATIONAL": [
              {
                "name": "NOM",
                "declaredType": "java.lang.String",
                "scope": "fr.gouv.dila.opendata.api.model.Boamp.Boamp_v110.Identite",
                "value": "GME EUROVIA/FAMY, ",
                "nil": false,
                "globalScope": false,
                "typeSubstituted": false
              },
              {
                "name": "ADRESSE",
                "declaredType": "java.lang.String",
                "scope": "fr.gouv.dila.opendata.api.model.Boamp.Boamp_v110.Identite",
                "value": "136 All\u00e9e Bonates, ",
                "nil": false,
                "globalScope": false,
                "typeSubstituted": false
              },
              {
                "name": "CP",
                "declaredType": "java.lang.String",
                "scope": "fr.gouv.dila.opendata.api.model.Boamp.Boamp_v110.Identite",
                "value": "01440",
                "nil": false,
                "globalScope": false,
                "typeSubstituted": false
              },
              {
                "name": "VILLE",
                "declaredType": "java.lang.String",
                "scope": "fr.gouv.dila.opendata.api.model.Boamp.Boamp_v110.Identite",
                "value": "Viriat.",
                "nil": false,
                "globalScope": false,
                "typeSubstituted": false
              }
            ]
          },
          "nil": false,
          "globalScope": false,
          "typeSubstituted": false
        },
        {
          "name": "INFO",
          "declaredType": "fr.gouv.dila.opendata.api.model.Boamp.Boamp_v110.Info",
          "scope": "fr.gouv.dila.opendata.api.model.Boamp.Boamp_v110.Annonce$DONNEES",
          "value": {
            "travauxandFOURNITURESAndSERVICES": [
              {
                "name": "PUBLICATIONS",
                "declaredType": "fr.gouv.dila.opendata.api.model.Boamp.Boamp_v110.Info$PUBLICATIONS",
                "scope": "fr.gouv.dila.opendata.api.model.Boamp.Boamp_v110.Info",
                "value": {
                  "publication": [
                    {
                      "parutionandEDITIONAndANNONCE": [
                        {
                          "name": "PARUTION",
                          "declaredType": "java.lang.String",
                          "scope": "fr.gouv.dila.opendata.api.model.Boamp.Boamp_v110.Info$PUBLICATIONS$PUBLICATION",
                          "value": "091 A",
                          "nil": false,
                          "globalScope": false,
                          "typeSubstituted": false
                        },
                        {
                          "name": "ANNONCE",
                          "declaredType": "java.lang.String",
                          "scope": "fr.gouv.dila.opendata.api.model.Boamp.Boamp_v110.Info$PUBLICATIONS$PUBLICATION",
                          "value": "99",
                          "nil": false,
                          "globalScope": false,
                          "typeSubstituted": false
                        },
                        {
                          "name": "DATE",
                          "declaredType": "java.lang.String",
                          "scope": "fr.gouv.dila.opendata.api.model.Boamp.Boamp_v110.Info$PUBLICATIONS$PUBLICATION",
                          "value": "10 mai 2008",
                          "nil": false,
                          "globalScope": false,
                          "typeSubstituted": false
                        }
                      ]
                    }
                  ]
                },
                "nil": false,
                "globalScope": false,
                "typeSubstituted": false
              }
            ]
          },
          "nil": false,
          "globalScope": false,
          "typeSubstituted": false
        },
        {
          "name": "CLASSES",
          "declaredType": "fr.gouv.dila.opendata.api.model.Boamp.Boamp_v110.Classes",
          "scope": "fr.gouv.dila.opendata.api.model.Boamp.Boamp_v110.Annonce$DONNEES",
          "value": {
            "classe": [
              "Travaux de construction"
            ]
          },
          "nil": false,
          "globalScope": false,
          "typeSubstituted": false
        },
        {
          "name": "DESCRIPTEURS",
          "declaredType": "fr.gouv.dila.opendata.api.model.Boamp.Boamp_v110.Annonce$DONNEES$DESCRIPTEURS",
          "scope": "fr.gouv.dila.opendata.api.model.Boamp.Boamp_v110.Annonce$DONNEES",
          "value": {
            "descripteur": [
              "Assainissement",
              "Terrassement"
            ]
          },
          "nil": false,
          "globalScope": false,
          "typeSubstituted": false
        },
        {
          "name": "AUTRES",
          "declaredType": "java.lang.String",
          "scope": "fr.gouv.dila.opendata.api.model.Boamp.Boamp_v110.Annonce$DONNEES",
          "value": "01 am\u00e9nagement de la rd 1075 entre bourg en bresse et la vavrette giratoire des douvres",
          "nil": false,
          "globalScope": false,
          "typeSubstituted": false
        }
      ]
    }
  },
  "nompublication": "BOMP C",
  "dateparution": "18 septembre 2008",
  "numparution": "20080075"
}